nanocr/__init__.py
nanocr/app/__init__.py
nanocr/app/args.py
nanocr/app/pdf2md.py
nanocr/app/utils.py
nanocr/core/__init__.py
nanocr/core/client.py
nanocr/core/confidence.py
nanocr/core/config.py
nanocr/core/extract.py
nanocr/core/prompts.py
nanocr/core/utils.py
nanocr/core/vllm.py
nanocr/core/file_converters/__init__.py
nanocr/core/file_converters/file_converter.py
nanocr/core/file_converters/pdf_converter.py
nanocr/core/pdf2md/__init__.py
nanocr/core/pdf2md/pdf2md.py
nanocr-0.0.2.dist-info/LICENSE
nanocr-0.0.2.dist-info/WHEEL
nanocr-0.0.2.dist-info/METADATA
nanocr-0.0.2.dist-info/RECORD
