Metadata-Version: 2.1
Name: nanocr
Version: 0.0.2
Summary: nano/tiny ocr model
Author-email: calcuis <info@calcu.io>
Classifier: License :: OSI Approved :: MIT License
Project-URL: Repository, https://github.com/calcuis/ocr-test-model
